newapp/__init__.py
newapp/apps.py
newapp/tests.py
newapp/utils.py
newapp/app_templates/complex/__init__.py
newapp/app_templates/complex/admin.py
newapp/app_templates/complex/apps.py
newapp/app_templates/complex/desc.txt
newapp/app_templates/complex/migrations/__init__.py
newapp/app_templates/complex/models/__init__.py
newapp/app_templates/complex/signals/__init__.py
newapp/app_templates/complex/urls/__init__.py
newapp/app_templates/complex/views/__init__.py
newapp/app_templates/drf_lite/__init__.py
newapp/app_templates/drf_lite/admin.py
newapp/app_templates/drf_lite/apps.py
newapp/app_templates/drf_lite/desc.txt
newapp/app_templates/drf_lite/models.py
newapp/app_templates/drf_lite/serializers.py
newapp/app_templates/drf_lite/signals.py
newapp/app_templates/drf_lite/urls.py
newapp/app_templates/drf_lite/views.py
newapp/app_templates/drf_lite/migrations/__init__.py
newapp/app_templates/lite/__init__.py
newapp/app_templates/lite/admin.py
newapp/app_templates/lite/apps.py
newapp/app_templates/lite/desc.txt
newapp/app_templates/lite/models.py
newapp/app_templates/lite/signals.py
newapp/app_templates/lite/urls.py
newapp/app_templates/lite/views.py
newapp/app_templates/lite/migrations/__init__.py
newapp/management/__init__.py
newapp/management/commands/__init__.py
newapp/management/commands/listapptype.py
newapp/management/commands/newapp.py
django_newapp-0.9.2.dist-info/METADATA
django_newapp-0.9.2.dist-info/WHEEL
django_newapp-0.9.2.dist-info/top_level.txt
django_newapp-0.9.2.dist-info/RECORD
